<?xml version="1.0" encoding="utf-8" ?>
<LanguageData>

	<Deterioration.label>рана</Deterioration.label>
	<Deterioration.deathMessage>{0} почина.</Deterioration.deathMessage>

	<Mining.label>мина</Mining.label>
	<Mining.deathMessage>{0} почина.</Mining.deathMessage>

	<Rotting.label>разлагане</Rotting.label>
	<Rotting.deathMessage>{0} почина.</Rotting.deathMessage>

	<Extinguish.label>задушаване</Extinguish.label>
	<Extinguish.deathMessage>{0} почина.</Extinguish.deathMessage>

	<Bomb.label>взрив</Bomb.label>
	<Bomb.deathMessage>{0} почина от експлозия.</Bomb.deathMessage>

	<Smoke.label>дим</Smoke.label>
	<Smoke.deathMessage>{0} задушен от дим.</Smoke.deathMessage>

</LanguageData>
